physicsbox/__init__.py
physicsbox/focus_analysis.py
physicsbox/hdr_stacking.py
physicsbox/image_analysis.py
physicsbox/misc.py
physicsbox/tictoc.py
physicsbox/units.py
physicsbox/utils.py
physicsbox/oap/__init__.py
physicsbox/oap/oap_class.py
physicsbox/oap/oap_class_no_approx.py
physicsbox/oap/utils.py
physicsbox/optics/__init__.py
physicsbox/optics/airybeams.py
physicsbox/optics/gaussbeams.py
physicsbox/optics/laserpulses.py
physicsbox/optics/simple_fields.py
physicsbox/optics/utilities.py
physicsbox/relativity/__init__.py
physicsbox/wavefronts/__init__.py
physicsbox/wavefronts/baseclasses.py
physicsbox/wavefronts/helpers.py
physicsbox/wavefronts/imageevaluation.py
physicsbox/wavefronts/interpnan.py
physicsbox/wavefronts/pipeline.py
physicsbox/wavefronts/postprocessing.py
physicsbox/wavefronts/wavefrontreconstructor.py
physicsbox/wavefronts/zernikefit.py
physicsbox-0.5.0.dist-info/licenses/LICENSE.txt
physicsbox-0.5.0.dist-info/METADATA
physicsbox-0.5.0.dist-info/WHEEL
physicsbox-0.5.0.dist-info/top_level.txt
physicsbox-0.5.0.dist-info/RECORD
