Metadata-Version: 2.4
Name: physicsbox
Version: 0.5.0
Summary: Collection of useful calculations for optics and more.
Author-email: Leonard Doyle <leonard.doyle@physik.uni-muenchen.de>
License-Expression: MIT
Project-URL: Homepage, https://gitlab.lrz.de/cala-public/packages/physicsbox
Project-URL: Issues, https://gitlab.lrz.de/cala-public/packages/physicsbox/-/issues
Classifier: Programming Language :: Python :: 3
Classifier: Operating System :: OS Independent
Requires-Python: >=3.8
License-File: LICENSE.txt
Requires-Dist: numpy
Requires-Dist: scipy
Provides-Extra: full
Requires-Dist: matplotlib; extra == "full"
Requires-Dist: LightPipes; extra == "full"
Requires-Dist: scikit-image; extra == "full"
Requires-Dist: numba; extra == "full"
Requires-Dist: numba-progress; extra == "full"
Dynamic: license-file
